src/__init__.py
src/hyperplanes/__init__.py
src/hyperplanes/planes.py
src/hyperplanes/systems.py
src/learner/__init__.py
src/learner/expressions.py
src/learner/polylearner.py
src/learner/symbolicsystems.py
src/learner/prolog/__init__.py
src/learner/prolog/polylearner.py
polylearner-0.1.1.dist-info/METADATA
polylearner-0.1.1.dist-info/WHEEL
polylearner-0.1.1.dist-info/licenses/LICENSE
polylearner-0.1.1.dist-info/RECORD
