Metadata-Version: 2.1
Name: polylearner
Version: 0.1.1
Summary: Learning from polyhedra: generalize multiple polyhedra into a parametric polyhedron.
Project-URL: Homepage, https://github.com/msetzu/polylearner
Project-URL: Bug Tracker, https://github.com/msetzu/polylearner/issues
Author-email: Mattia Setzu <mattia.setzu@unipi.it>
License-File: LICENSE
Classifier: Development Status :: 4 - Beta
Classifier: Intended Audience :: Developers
Classifier: License :: OSI Approved :: GNU General Public License v3 or later (GPLv3+)
Classifier: Operating System :: OS Independent
Classifier: Programming Language :: Python :: 3.11
Requires-Python: <=3.11,>3.10
Requires-Dist: numpy>=1.23.5
Requires-Dist: swiplserver>=1.0.2
